[["2017-05-05", [{"venue": "Coles", "artist_name": "Desert Limina", "band_img": "https://mohawkaustin.com/_/made/_/remote/https_res.\t\t\t\t\t\t\tcloudinary.com/hjbfjdt7p/image/upload/c_fill,w_470/v1467240024/neqbteulerpqi\t\t\t\t\t\t\tkkcroeb_256_256_80_s_c1_c_t_0_0_1.jpg", "event_id": "30023214", "artist_id": 9100034, "time": "19:00:00", "venue_img": "coles"}, {"venue": "Quenchers", "artist_name": "Den", "band_img": "https://mohawkaustin.com/_/made/_/remote/https_res.\t\t\t\t\t\t\tcloudinary.com/hjbfjdt7p/image/upload/c_fill,w_470/v1467240024/neqbteulerpqi\t\t\t\t\t\t\tkkcroeb_256_256_80_s_c1_c_t_0_0_1.jpg", "event_id": "29742739", "artist_id": 460740, "time": "21:00:00", "venue_img": "quenchers"}, {"venue": "Bottom Lounge", "artist_name": "The King of Mars", "band_img": "https://mohawkaustin.com/_/made/_/remote/https_res.\t\t\t\t\t\t\tcloudinary.com/hjbfjdt7p/image/upload/c_fill,w_470/v1467240024/neqbteulerpqi\t\t\t\t\t\t\tkkcroeb_256_256_80_s_c1_c_t_0_0_1.jpg", "event_id": "29840309", "artist_id": 8818689, "time": "21:00:00", "venue_img": "bottom-lounge"}, {"venue": "Subterranean", "artist_name": "Murs", "band_img": "https://mohawkaustin.com/_/made/_/remote/https_res.\t\t\t\t\t\t\tcloudinary.com/hjbfjdt7p/image/upload/c_fill,w_470/v1467240024/neqbteulerpqi\t\t\t\t\t\t\tkkcroeb_256_256_80_s_c1_c_t_0_0_1.jpg", "event_id": "29458964", "artist_id": 82388, "time": "21:00:00", "venue_img": "subterranean"}, {"venue": "Beat Kitchen", "artist_name": "White Reaper", "band_img": "https://mohawkaustin.com/_/made/_/remote/https_res.\t\t\t\t\t\t\tcloudinary.com/hjbfjdt7p/image/upload/c_fill,w_470/v1467240024/neqbteulerpqi\t\t\t\t\t\t\tkkcroeb_256_256_80_s_c1_c_t_0_0_1.jpg", "event_id": "29537874", "artist_id": 6119854, "time": null, "venue_img": "beat-kitchen"}, {"venue": "Lincoln Hall", "artist_name": "Fenech-Soler", "band_img": "https://mohawkaustin.com/_/made/_/remote/https_res.\t\t\t\t\t\t\tcloudinary.com/hjbfjdt7p/image/upload/c_fill,w_470/v1467240024/neqbteulerpqi\t\t\t\t\t\t\tkkcroeb_256_256_80_s_c1_c_t_0_0_1.jpg", "event_id": "29595849", "artist_id": 2382528, "time": null, "venue_img": "lincoln-hall"}, {"venue": "Schubas", "artist_name": "Peter Bradley Adams", "band_img": "https://mohawkaustin.com/_/made/_/remote/https_res.\t\t\t\t\t\t\tcloudinary.com/hjbfjdt7p/image/upload/c_fill,w_470/v1467240024/neqbteulerpqi\t\t\t\t\t\t\tkkcroeb_256_256_80_s_c1_c_t_0_0_1.jpg", "event_id": "29297594", "artist_id": 376671, "time": null, "venue_img": "schubas"}, {"venue": "Schubas", "artist_name": "Wild Adriatic", "band_img": "https://mohawkaustin.com/_/made/_/remote/https_res.\t\t\t\t\t\t\tcloudinary.com/hjbfjdt7p/image/upload/c_fill,w_470/v1467240024/neqbteulerpqi\t\t\t\t\t\t\tkkcroeb_256_256_80_s_c1_c_t_0_0_1.jpg", "event_id": "29646649", "artist_id": 4988089, "time": "22:00:00", "venue_img": "schubas"}, {"venue": "Schubas", "artist_name": "Horrible", "band_img": "https://mohawkaustin.com/_/made/_/remote/https_res.\t\t\t\t\t\t\tcloudinary.com/hjbfjdt7p/image/upload/c_fill,w_470/v1467240024/neqbteulerpqi\t\t\t\t\t\t\tkkcroeb_256_256_80_s_c1_c_t_0_0_1.jpg", "event_id": "30039939", "artist_id": 7121629, "time": "21:00:00", "venue_img": "schubas"}, {"venue": "Thalia Hall", "artist_name": "The Mavericks", "band_img": "https://mohawkaustin.com/_/made/_/remote/https_res.\t\t\t\t\t\t\tcloudinary.com/hjbfjdt7p/image/upload/c_fill,w_470/v1467240024/neqbteulerpqi\t\t\t\t\t\t\tkkcroeb_256_256_80_s_c1_c_t_0_0_1.jpg", "event_id": "28931484", "artist_id": 439914, "time": "20:00:00", "venue_img": "thalia-hall"}, {"venue": "The Hideout", "artist_name": "The Interview Show Hosted By Mark Bazer", "band_img": "https://mohawkaustin.com/_/made/_/remote/https_res.\t\t\t\t\t\t\tcloudinary.com/hjbfjdt7p/image/upload/c_fill,w_470/v1467240024/neqbteulerpqi\t\t\t\t\t\t\tkkcroeb_256_256_80_s_c1_c_t_0_0_1.jpg", "event_id": "29802064", "artist_id": 3857236, "time": "18:30:00", "venue_img": "hideout"}]], ["2017-05-06", [{"venue": "Empty Bottle", "artist_name": "Crown Larks", "band_img": "https://mohawkaustin.com/_/made/_/remote/https_res.\t\t\t\t\t\t\tcloudinary.com/hjbfjdt7p/image/upload/c_fill,w_470/v1467240024/neqbteulerpqi\t\t\t\t\t\t\tkkcroeb_256_256_80_s_c1_c_t_0_0_1.jpg", "event_id": "29599714", "artist_id": 6133294, "time": "21:00:00", "venue_img": "empty-bottle"}, {"venue": "Quenchers", "artist_name": "Alouette", "band_img": "https://mohawkaustin.com/_/made/_/remote/https_res.\t\t\t\t\t\t\tcloudinary.com/hjbfjdt7p/image/upload/c_fill,w_470/v1467240024/neqbteulerpqi\t\t\t\t\t\t\tkkcroeb_256_256_80_s_c1_c_t_0_0_1.jpg", "event_id": "29495934", "artist_id": 5858414, "time": null, "venue_img": "quenchers"}, {"venue": "Bottom Lounge", "artist_name": "KILLING GODS", "band_img": "https://mohawkaustin.com/_/made/_/remote/https_res.\t\t\t\t\t\t\tcloudinary.com/hjbfjdt7p/image/upload/c_fill,w_470/v1467240024/neqbteulerpqi\t\t\t\t\t\t\tkkcroeb_256_256_80_s_c1_c_t_0_0_1.jpg", "event_id": "29719034", "artist_id": 6792509, "time": "19:30:00", "venue_img": "bottom-lounge"}, {"venue": "Subterranean", "artist_name": "Music Tapes", "band_img": "https://mohawkaustin.com/_/made/_/remote/https_res.\t\t\t\t\t\t\tcloudinary.com/hjbfjdt7p/image/upload/c_fill,w_470/v1467240024/neqbteulerpqi\t\t\t\t\t\t\tkkcroeb_256_256_80_s_c1_c_t_0_0_1.jpg", "event_id": "29849844", "artist_id": 47146, "time": null, "venue_img": "subterranean"}, {"venue": "Beat Kitchen", "artist_name": "The Clarks", "band_img": "https://mohawkaustin.com/_/made/_/remote/https_res.\t\t\t\t\t\t\tcloudinary.com/hjbfjdt7p/image/upload/c_fill,w_470/v1467240024/neqbteulerpqi\t\t\t\t\t\t\tkkcroeb_256_256_80_s_c1_c_t_0_0_1.jpg", "event_id": "29239084", "artist_id": 369221, "time": "21:00:00", "venue_img": "beat-kitchen"}, {"venue": "Schubas", "artist_name": "Froth", "band_img": "https://mohawkaustin.com/_/made/_/remote/https_res.\t\t\t\t\t\t\tcloudinary.com/hjbfjdt7p/image/upload/c_fill,w_470/v1467240024/neqbteulerpqi\t\t\t\t\t\t\tkkcroeb_256_256_80_s_c1_c_t_0_0_1.jpg", "event_id": "29381979", "artist_id": 1387517, "time": null, "venue_img": "schubas"}, {"venue": "Thalia Hall", "artist_name": "Lewis Del Mar", "band_img": "https://mohawkaustin.com/_/made/_/remote/https_res.\t\t\t\t\t\t\tcloudinary.com/hjbfjdt7p/image/upload/c_fill,w_470/v1467240024/neqbteulerpqi\t\t\t\t\t\t\tkkcroeb_256_256_80_s_c1_c_t_0_0_1.jpg", "event_id": "29157249", "artist_id": 8582034, "time": "20:00:00", "venue_img": "thalia-hall"}, {"venue": "The Hideout", "artist_name": "The Poison Arrows", "band_img": "https://mohawkaustin.com/_/made/_/remote/https_res.\t\t\t\t\t\t\tcloudinary.com/hjbfjdt7p/image/upload/c_fill,w_470/v1467240024/neqbteulerpqi\t\t\t\t\t\t\tkkcroeb_256_256_80_s_c1_c_t_0_0_1.jpg", "event_id": "29641749", "artist_id": 802296, "time": "21:00:00", "venue_img": "hideout"}]], ["2017-05-07", [{"venue": "Empty Bottle", "artist_name": "Laser Background", "band_img": "https://mohawkaustin.com/_/made/_/remote/https_res.\t\t\t\t\t\t\tcloudinary.com/hjbfjdt7p/image/upload/c_fill,w_470/v1467240024/neqbteulerpqi\t\t\t\t\t\t\tkkcroeb_256_256_80_s_c1_c_t_0_0_1.jpg", "event_id": "29460559", "artist_id": 5327338, "time": null, "venue_img": "empty-bottle"}, {"venue": "The Burlington", "artist_name": "Wick & The Tricks", "band_img": "https://mohawkaustin.com/_/made/_/remote/https_res.\t\t\t\t\t\t\tcloudinary.com/hjbfjdt7p/image/upload/c_fill,w_470/v1467240024/neqbteulerpqi\t\t\t\t\t\t\tkkcroeb_256_256_80_s_c1_c_t_0_0_1.jpg", "event_id": "29769574", "artist_id": 5985824, "time": null, "venue_img": "burlington"}]], ["2017-05-08", [{"venue": "Beat Kitchen", "artist_name": "Extraordinary Popular Delusions", "band_img": "https://mohawkaustin.com/_/made/_/remote/https_res.\t\t\t\t\t\t\tcloudinary.com/hjbfjdt7p/image/upload/c_fill,w_470/v1467240024/neqbteulerpqi\t\t\t\t\t\t\tkkcroeb_256_256_80_s_c1_c_t_0_0_1.jpg", "event_id": "29979049", "artist_id": 3099761, "time": "21:00:00", "venue_img": "beat-kitchen"}, {"venue": "Schubas", "artist_name": "The Wild Reeds", "band_img": "https://mohawkaustin.com/_/made/_/remote/https_res.\t\t\t\t\t\t\tcloudinary.com/hjbfjdt7p/image/upload/c_fill,w_470/v1467240024/neqbteulerpqi\t\t\t\t\t\t\tkkcroeb_256_256_80_s_c1_c_t_0_0_1.jpg", "event_id": "28994499", "artist_id": 3457426, "time": "19:30:00", "venue_img": "schubas"}, {"venue": "The Burlington", "artist_name": "Zach Puls", "band_img": "https://mohawkaustin.com/_/made/_/remote/https_res.\t\t\t\t\t\t\tcloudinary.com/hjbfjdt7p/image/upload/c_fill,w_470/v1467240024/neqbteulerpqi\t\t\t\t\t\t\tkkcroeb_256_256_80_s_c1_c_t_0_0_1.jpg", "event_id": "30065589", "artist_id": 9104399, "time": "19:00:00", "venue_img": "burlington"}]], ["2017-05-09", [{"venue": "Empty Bottle", "artist_name": "Demdike Stare", "band_img": "https://mohawkaustin.com/_/made/_/remote/https_res.\t\t\t\t\t\t\tcloudinary.com/hjbfjdt7p/image/upload/c_fill,w_470/v1467240024/neqbteulerpqi\t\t\t\t\t\t\tkkcroeb_256_256_80_s_c1_c_t_0_0_1.jpg", "event_id": "29599799", "artist_id": 2915616, "time": "21:00:00", "venue_img": "empty-bottle"}, {"venue": "Lincoln Hall", "artist_name": "Gavin James", "band_img": "https://mohawkaustin.com/_/made/_/remote/https_res.\t\t\t\t\t\t\tcloudinary.com/hjbfjdt7p/image/upload/c_fill,w_470/v1467240024/neqbteulerpqi\t\t\t\t\t\t\tkkcroeb_256_256_80_s_c1_c_t_0_0_1.jpg", "event_id": "29781549", "artist_id": 6069699, "time": "19:00:00", "venue_img": "lincoln-hall"}, {"venue": "The Hideout", "artist_name": "David Singer & The Sweet Science", "band_img": "https://mohawkaustin.com/_/made/_/remote/https_res.\t\t\t\t\t\t\tcloudinary.com/hjbfjdt7p/image/upload/c_fill,w_470/v1467240024/neqbteulerpqi\t\t\t\t\t\t\tkkcroeb_256_256_80_s_c1_c_t_0_0_1.jpg", "event_id": "29774839", "artist_id": 251650, "time": "21:00:00", "venue_img": "hideout"}, {"venue": "The Hideout", "artist_name": "Write Club", "band_img": "https://mohawkaustin.com/_/made/_/remote/https_res.\t\t\t\t\t\t\tcloudinary.com/hjbfjdt7p/image/upload/c_fill,w_470/v1467240024/neqbteulerpqi\t\t\t\t\t\t\tkkcroeb_256_256_80_s_c1_c_t_0_0_1.jpg", "event_id": "29943949", "artist_id": 3678186, "time": "19:00:00", "venue_img": "hideout"}]], ["2017-05-10", [{"venue": "Empty Bottle", "artist_name": "Mystic Braves", "band_img": "https://mohawkaustin.com/_/made/_/remote/https_res.\t\t\t\t\t\t\tcloudinary.com/hjbfjdt7p/image/upload/c_fill,w_470/v1467240024/neqbteulerpqi\t\t\t\t\t\t\tkkcroeb_256_256_80_s_c1_c_t_0_0_1.jpg", "event_id": "29583039", "artist_id": 7038644, "time": null, "venue_img": "empty-bottle"}, {"venue": "Quenchers", "artist_name": "Erzulie", "band_img": "https://mohawkaustin.com/_/made/_/remote/https_res.\t\t\t\t\t\t\tcloudinary.com/hjbfjdt7p/image/upload/c_fill,w_470/v1467240024/neqbteulerpqi\t\t\t\t\t\t\tkkcroeb_256_256_80_s_c1_c_t_0_0_1.jpg", "event_id": "29962599", "artist_id": 8714609, "time": "21:00:00", "venue_img": "quenchers"}, {"venue": "Subterranean", "artist_name": "Roots of Creation", "band_img": "https://mohawkaustin.com/_/made/_/remote/https_res.\t\t\t\t\t\t\tcloudinary.com/hjbfjdt7p/image/upload/c_fill,w_470/v1467240024/neqbteulerpqi\t\t\t\t\t\t\tkkcroeb_256_256_80_s_c1_c_t_0_0_1.jpg", "event_id": "29867614", "artist_id": 594157, "time": "20:00:00", "venue_img": "subterranean"}, {"venue": "Beat Kitchen", "artist_name": "River Oaks", "band_img": "https://mohawkaustin.com/_/made/_/remote/https_res.\t\t\t\t\t\t\tcloudinary.com/hjbfjdt7p/image/upload/c_fill,w_470/v1467240024/neqbteulerpqi\t\t\t\t\t\t\tkkcroeb_256_256_80_s_c1_c_t_0_0_1.jpg", "event_id": "29432149", "artist_id": 1162784, "time": "19:00:00", "venue_img": "beat-kitchen"}, {"venue": "Lincoln Hall", "artist_name": "Neil Hamburger", "band_img": "https://mohawkaustin.com/_/made/_/remote/https_res.\t\t\t\t\t\t\tcloudinary.com/hjbfjdt7p/image/upload/c_fill,w_470/v1467240024/neqbteulerpqi\t\t\t\t\t\t\tkkcroeb_256_256_80_s_c1_c_t_0_0_1.jpg", "event_id": "29687114", "artist_id": 303904, "time": "19:00:00", "venue_img": "lincoln-hall"}, {"venue": "The Hideout", "artist_name": "Wei Zhongle", "band_img": "https://mohawkaustin.com/_/made/_/remote/https_res.\t\t\t\t\t\t\tcloudinary.com/hjbfjdt7p/image/upload/c_fill,w_470/v1467240024/neqbteulerpqi\t\t\t\t\t\t\tkkcroeb_256_256_80_s_c1_c_t_0_0_1.jpg", "event_id": "29653964", "artist_id": 4796163, "time": "21:00:00", "venue_img": "hideout"}]], ["2017-05-11", [{"venue": "Empty Bottle", "artist_name": "Redd Kross", "band_img": "https://mohawkaustin.com/_/made/_/remote/https_res.\t\t\t\t\t\t\tcloudinary.com/hjbfjdt7p/image/upload/c_fill,w_470/v1467240024/neqbteulerpqi\t\t\t\t\t\t\tkkcroeb_256_256_80_s_c1_c_t_0_0_1.jpg", "event_id": "29342604", "artist_id": 445659, "time": "21:00:00", "venue_img": "empty-bottle"}, {"venue": "Bottom Lounge", "artist_name": "Mat Kerekes", "band_img": "https://mohawkaustin.com/_/made/_/remote/https_res.\t\t\t\t\t\t\tcloudinary.com/hjbfjdt7p/image/upload/c_fill,w_470/v1467240024/neqbteulerpqi\t\t\t\t\t\t\tkkcroeb_256_256_80_s_c1_c_t_0_0_1.jpg", "event_id": "29531024", "artist_id": 8073918, "time": "18:30:00", "venue_img": "bottom-lounge"}, {"venue": "Subterranean", "artist_name": "Pile", "band_img": "https://mohawkaustin.com/_/made/_/remote/https_res.\t\t\t\t\t\t\tcloudinary.com/hjbfjdt7p/image/upload/c_fill,w_470/v1467240024/neqbteulerpqi\t\t\t\t\t\t\tkkcroeb_256_256_80_s_c1_c_t_0_0_1.jpg", "event_id": "29046949", "artist_id": 324214, "time": null, "venue_img": "subterranean"}, {"venue": "Beat Kitchen", "artist_name": "Yoko and the Oh No's", "band_img": "https://mohawkaustin.com/_/made/_/remote/https_res.\t\t\t\t\t\t\tcloudinary.com/hjbfjdt7p/image/upload/c_fill,w_470/v1467240024/neqbteulerpqi\t\t\t\t\t\t\tkkcroeb_256_256_80_s_c1_c_t_0_0_1.jpg", "event_id": "29641834", "artist_id": 5669759, "time": "20:30:00", "venue_img": "beat-kitchen"}, {"venue": "Lincoln Hall", "artist_name": "Lewis Watson", "band_img": "https://mohawkaustin.com/_/made/_/remote/https_res.\t\t\t\t\t\t\tcloudinary.com/hjbfjdt7p/image/upload/c_fill,w_470/v1467240024/neqbteulerpqi\t\t\t\t\t\t\tkkcroeb_256_256_80_s_c1_c_t_0_0_1.jpg", "event_id": "29885369", "artist_id": 4684853, "time": "18:00:00", "venue_img": "lincoln-hall"}, {"venue": "Thalia Hall", "artist_name": "The Black Angels", "band_img": "https://mohawkaustin.com/_/made/_/remote/https_res.\t\t\t\t\t\t\tcloudinary.com/hjbfjdt7p/image/upload/c_fill,w_470/v1467240024/neqbteulerpqi\t\t\t\t\t\t\tkkcroeb_256_256_80_s_c1_c_t_0_0_1.jpg", "event_id": "29220544", "artist_id": 443460, "time": null, "venue_img": "thalia-hall"}, {"venue": "The Hideout", "artist_name": "VARSITY", "band_img": "https://mohawkaustin.com/_/made/_/remote/https_res.\t\t\t\t\t\t\tcloudinary.com/hjbfjdt7p/image/upload/c_fill,w_470/v1467240024/neqbteulerpqi\t\t\t\t\t\t\tkkcroeb_256_256_80_s_c1_c_t_0_0_1.jpg", "event_id": "29612924", "artist_id": 598013, "time": "21:00:00", "venue_img": "hideout"}, {"venue": "The Hideout", "artist_name": "Devil in a Woodpile", "band_img": "https://mohawkaustin.com/_/made/_/remote/https_res.\t\t\t\t\t\t\tcloudinary.com/hjbfjdt7p/image/upload/c_fill,w_470/v1467240024/neqbteulerpqi\t\t\t\t\t\t\tkkcroeb_256_256_80_s_c1_c_t_0_0_1.jpg", "event_id": "29949024", "artist_id": 199723, "time": "18:00:00", "venue_img": "hideout"}]], ["2017-05-12", [{"venue": "Empty Bottle", "artist_name": "Kikagaku Moyo", "band_img": "https://mohawkaustin.com/_/made/_/remote/https_res.\t\t\t\t\t\t\tcloudinary.com/hjbfjdt7p/image/upload/c_fill,w_470/v1467240024/neqbteulerpqi\t\t\t\t\t\t\tkkcroeb_256_256_80_s_c1_c_t_0_0_1.jpg", "event_id": "29456774", "artist_id": 6750884, "time": "21:00:00", "venue_img": "empty-bottle"}, {"venue": "Quenchers", "artist_name": "Sadie and the Stark", "band_img": "https://mohawkaustin.com/_/made/_/remote/https_res.\t\t\t\t\t\t\tcloudinary.com/hjbfjdt7p/image/upload/c_fill,w_470/v1467240024/neqbteulerpqi\t\t\t\t\t\t\tkkcroeb_256_256_80_s_c1_c_t_0_0_1.jpg", "event_id": "29611899", "artist_id": 8233793, "time": "21:00:00", "venue_img": "quenchers"}, {"venue": "Bottom Lounge", "artist_name": "Ab-Soul", "band_img": "https://mohawkaustin.com/_/made/_/remote/https_res.\t\t\t\t\t\t\tcloudinary.com/hjbfjdt7p/image/upload/c_fill,w_470/v1467240024/neqbteulerpqi\t\t\t\t\t\t\tkkcroeb_256_256_80_s_c1_c_t_0_0_1.jpg", "event_id": "29727699", "artist_id": 876610, "time": null, "venue_img": "bottom-lounge"}, {"venue": "Subterranean", "artist_name": "The War on Peace", "band_img": "https://mohawkaustin.com/_/made/_/remote/https_res.\t\t\t\t\t\t\tcloudinary.com/hjbfjdt7p/image/upload/c_fill,w_470/v1467240024/neqbteulerpqi\t\t\t\t\t\t\tkkcroeb_256_256_80_s_c1_c_t_0_0_1.jpg", "event_id": "29612959", "artist_id": 8519493, "time": "21:00:00", "venue_img": "subterranean"}, {"venue": "Beat Kitchen", "artist_name": "Chastity", "band_img": "https://mohawkaustin.com/_/made/_/remote/https_res.\t\t\t\t\t\t\tcloudinary.com/hjbfjdt7p/image/upload/c_fill,w_470/v1467240024/neqbteulerpqi\t\t\t\t\t\t\tkkcroeb_256_256_80_s_c1_c_t_0_0_1.jpg", "event_id": "29445314", "artist_id": 676072, "time": "20:30:00", "venue_img": "beat-kitchen"}, {"venue": "Lincoln Hall", "artist_name": "The Giving Tree Band", "band_img": "https://mohawkaustin.com/_/made/_/remote/https_res.\t\t\t\t\t\t\tcloudinary.com/hjbfjdt7p/image/upload/c_fill,w_470/v1467240024/neqbteulerpqi\t\t\t\t\t\t\tkkcroeb_256_256_80_s_c1_c_t_0_0_1.jpg", "event_id": "29454644", "artist_id": 487740, "time": "20:00:00", "venue_img": "lincoln-hall"}, {"venue": "Schubas", "artist_name": "Leif Vollebekk", "band_img": "https://mohawkaustin.com/_/made/_/remote/https_res.\t\t\t\t\t\t\tcloudinary.com/hjbfjdt7p/image/upload/c_fill,w_470/v1467240024/neqbteulerpqi\t\t\t\t\t\t\tkkcroeb_256_256_80_s_c1_c_t_0_0_1.jpg", "event_id": "29255469", "artist_id": 2259751, "time": null, "venue_img": "schubas"}, {"venue": "Thalia Hall", "artist_name": "Old 97's", "band_img": "https://mohawkaustin.com/_/made/_/remote/https_res.\t\t\t\t\t\t\tcloudinary.com/hjbfjdt7p/image/upload/c_fill,w_470/v1467240024/neqbteulerpqi\t\t\t\t\t\t\tkkcroeb_256_256_80_s_c1_c_t_0_0_1.jpg", "event_id": "29104084", "artist_id": 308713, "time": "20:30:00", "venue_img": "thalia-hall"}, {"venue": "The Hideout", "artist_name": "Doug Tuttle", "band_img": "https://mohawkaustin.com/_/made/_/remote/https_res.\t\t\t\t\t\t\tcloudinary.com/hjbfjdt7p/image/upload/c_fill,w_470/v1467240024/neqbteulerpqi\t\t\t\t\t\t\tkkcroeb_256_256_80_s_c1_c_t_0_0_1.jpg", "event_id": "29459069", "artist_id": 7665739, "time": "21:00:00", "venue_img": "hideout"}, {"venue": "The Hideout", "artist_name": "Bunny Chicago", "band_img": "https://mohawkaustin.com/_/made/_/remote/https_res.\t\t\t\t\t\t\tcloudinary.com/hjbfjdt7p/image/upload/c_fill,w_470/v1467240024/neqbteulerpqi\t\t\t\t\t\t\tkkcroeb_256_256_80_s_c1_c_t_0_0_1.jpg", "event_id": "29477869", "artist_id": 8765259, "time": null, "venue_img": "hideout"}]], ["2017-05-13", [{"venue": "Empty Bottle", "artist_name": "Black Lips", "band_img": "https://mohawkaustin.com/_/made/_/remote/https_res.\t\t\t\t\t\t\tcloudinary.com/hjbfjdt7p/image/upload/c_fill,w_470/v1467240024/neqbteulerpqi\t\t\t\t\t\t\tkkcroeb_256_256_80_s_c1_c_t_0_0_1.jpg", "event_id": "29698544", "artist_id": 349473, "time": null, "venue_img": "empty-bottle"}, {"venue": "Quenchers", "artist_name": "The Flips", "band_img": "https://mohawkaustin.com/_/made/_/remote/https_res.\t\t\t\t\t\t\tcloudinary.com/hjbfjdt7p/image/upload/c_fill,w_470/v1467240024/neqbteulerpqi\t\t\t\t\t\t\tkkcroeb_256_256_80_s_c1_c_t_0_0_1.jpg", "event_id": "29848694", "artist_id": 640126, "time": "20:00:00", "venue_img": "quenchers"}, {"venue": "Beat Kitchen", "artist_name": "Holly Macve", "band_img": "https://mohawkaustin.com/_/made/_/remote/https_res.\t\t\t\t\t\t\tcloudinary.com/hjbfjdt7p/image/upload/c_fill,w_470/v1467240024/neqbteulerpqi\t\t\t\t\t\t\tkkcroeb_256_256_80_s_c1_c_t_0_0_1.jpg", "event_id": "29482734", "artist_id": 5830074, "time": "20:30:00", "venue_img": "beat-kitchen"}, {"venue": "Beat Kitchen", "artist_name": "Josefina Asconap\u00e9", "band_img": "https://mohawkaustin.com/_/made/_/remote/https_res.\t\t\t\t\t\t\tcloudinary.com/hjbfjdt7p/image/upload/c_fill,w_470/v1467240024/neqbteulerpqi\t\t\t\t\t\t\tkkcroeb_256_256_80_s_c1_c_t_0_0_1.jpg", "event_id": "30036244", "artist_id": 8115963, "time": null, "venue_img": "beat-kitchen"}, {"venue": "Lincoln Hall", "artist_name": "Andy Shauf", "band_img": "https://mohawkaustin.com/_/made/_/remote/https_res.\t\t\t\t\t\t\tcloudinary.com/hjbfjdt7p/image/upload/c_fill,w_470/v1467240024/neqbteulerpqi\t\t\t\t\t\t\tkkcroeb_256_256_80_s_c1_c_t_0_0_1.jpg", "event_id": "28715459", "artist_id": 1988796, "time": "20:30:00", "venue_img": "lincoln-hall"}, {"venue": "Schubas", "artist_name": "Charly Bliss", "band_img": "https://mohawkaustin.com/_/made/_/remote/https_res.\t\t\t\t\t\t\tcloudinary.com/hjbfjdt7p/image/upload/c_fill,w_470/v1467240024/neqbteulerpqi\t\t\t\t\t\t\tkkcroeb_256_256_80_s_c1_c_t_0_0_1.jpg", "event_id": "29253329", "artist_id": 5485523, "time": null, "venue_img": "schubas"}, {"venue": "The Burlington", "artist_name": "Bike Tuff", "band_img": "https://mohawkaustin.com/_/made/_/remote/https_res.\t\t\t\t\t\t\tcloudinary.com/hjbfjdt7p/image/upload/c_fill,w_470/v1467240024/neqbteulerpqi\t\t\t\t\t\t\tkkcroeb_256_256_80_s_c1_c_t_0_0_1.jpg", "event_id": "29219739", "artist_id": 4002846, "time": "19:00:00", "venue_img": "burlington"}, {"venue": "The Hideout", "artist_name": "The Ponderers", "band_img": "https://mohawkaustin.com/_/made/_/remote/https_res.\t\t\t\t\t\t\tcloudinary.com/hjbfjdt7p/image/upload/c_fill,w_470/v1467240024/neqbteulerpqi\t\t\t\t\t\t\tkkcroeb_256_256_80_s_c1_c_t_0_0_1.jpg", "event_id": "30003714", "artist_id": 8949789, "time": "23:59:00", "venue_img": "hideout"}]], ["2017-05-14", [{"venue": "Empty Bottle", "artist_name": "Black Lips", "band_img": "https://mohawkaustin.com/_/made/_/remote/https_res.\t\t\t\t\t\t\tcloudinary.com/hjbfjdt7p/image/upload/c_fill,w_470/v1467240024/neqbteulerpqi\t\t\t\t\t\t\tkkcroeb_256_256_80_s_c1_c_t_0_0_1.jpg", "event_id": "29698549", "artist_id": 349473, "time": null, "venue_img": "empty-bottle"}, {"venue": "Bottom Lounge", "artist_name": "Every Time I Die", "band_img": "https://mohawkaustin.com/_/made/_/remote/https_res.\t\t\t\t\t\t\tcloudinary.com/hjbfjdt7p/image/upload/c_fill,w_470/v1467240024/neqbteulerpqi\t\t\t\t\t\t\tkkcroeb_256_256_80_s_c1_c_t_0_0_1.jpg", "event_id": "29374049", "artist_id": 279699, "time": "18:00:00", "venue_img": "bottom-lounge"}, {"venue": "Thalia Hall", "artist_name": "Ty Segall", "band_img": "https://mohawkaustin.com/_/made/_/remote/https_res.\t\t\t\t\t\t\tcloudinary.com/hjbfjdt7p/image/upload/c_fill,w_470/v1467240024/neqbteulerpqi\t\t\t\t\t\t\tkkcroeb_256_256_80_s_c1_c_t_0_0_1.jpg", "event_id": "28565299", "artist_id": 964551, "time": null, "venue_img": "thalia-hall"}]], ["2017-05-15", [{"venue": "Empty Bottle", "artist_name": "The Besnard Lakes", "band_img": "https://mohawkaustin.com/_/made/_/remote/https_res.\t\t\t\t\t\t\tcloudinary.com/hjbfjdt7p/image/upload/c_fill,w_470/v1467240024/neqbteulerpqi\t\t\t\t\t\t\tkkcroeb_256_256_80_s_c1_c_t_0_0_1.jpg", "event_id": "29157379", "artist_id": 257647, "time": "21:00:00", "venue_img": "empty-bottle"}, {"venue": "Subterranean", "artist_name": "Goodbye June", "band_img": "https://mohawkaustin.com/_/made/_/remote/https_res.\t\t\t\t\t\t\tcloudinary.com/hjbfjdt7p/image/upload/c_fill,w_470/v1467240024/neqbteulerpqi\t\t\t\t\t\t\tkkcroeb_256_256_80_s_c1_c_t_0_0_1.jpg", "event_id": "29910894", "artist_id": 831215, "time": "19:30:00", "venue_img": "subterranean"}, {"venue": "Beat Kitchen", "artist_name": "Extraordinary Popular Delusions", "band_img": "https://mohawkaustin.com/_/made/_/remote/https_res.\t\t\t\t\t\t\tcloudinary.com/hjbfjdt7p/image/upload/c_fill,w_470/v1467240024/neqbteulerpqi\t\t\t\t\t\t\tkkcroeb_256_256_80_s_c1_c_t_0_0_1.jpg", "event_id": "29979539", "artist_id": 3099761, "time": "21:00:00", "venue_img": "beat-kitchen"}]], ["2017-05-16", [{"venue": "Empty Bottle", "artist_name": "HXLT", "band_img": "https://mohawkaustin.com/_/made/_/remote/https_res.\t\t\t\t\t\t\tcloudinary.com/hjbfjdt7p/image/upload/c_fill,w_470/v1467240024/neqbteulerpqi\t\t\t\t\t\t\tkkcroeb_256_256_80_s_c1_c_t_0_0_1.jpg", "event_id": "29898064", "artist_id": 9042124, "time": "21:00:00", "venue_img": "empty-bottle"}, {"venue": "Subterranean", "artist_name": "Beware of Darkness", "band_img": "https://mohawkaustin.com/_/made/_/remote/https_res.\t\t\t\t\t\t\tcloudinary.com/hjbfjdt7p/image/upload/c_fill,w_470/v1467240024/neqbteulerpqi\t\t\t\t\t\t\tkkcroeb_256_256_80_s_c1_c_t_0_0_1.jpg", "event_id": "29608209", "artist_id": 5252848, "time": null, "venue_img": "subterranean"}, {"venue": "Subterranean", "artist_name": "Frank Knight", "band_img": "https://mohawkaustin.com/_/made/_/remote/https_res.\t\t\t\t\t\t\tcloudinary.com/hjbfjdt7p/image/upload/c_fill,w_470/v1467240024/neqbteulerpqi\t\t\t\t\t\t\tkkcroeb_256_256_80_s_c1_c_t_0_0_1.jpg", "event_id": "30024319", "artist_id": 8336568, "time": "21:00:00", "venue_img": "subterranean"}, {"venue": "Beat Kitchen", "artist_name": "Splice Series", "band_img": "https://mohawkaustin.com/_/made/_/remote/https_res.\t\t\t\t\t\t\tcloudinary.com/hjbfjdt7p/image/upload/c_fill,w_470/v1467240024/neqbteulerpqi\t\t\t\t\t\t\tkkcroeb_256_256_80_s_c1_c_t_0_0_1.jpg", "event_id": "29899499", "artist_id": 8146923, "time": "21:00:00", "venue_img": "beat-kitchen"}, {"venue": "Lincoln Hall", "artist_name": "Mild High Club", "band_img": "https://mohawkaustin.com/_/made/_/remote/https_res.\t\t\t\t\t\t\tcloudinary.com/hjbfjdt7p/image/upload/c_fill,w_470/v1467240024/neqbteulerpqi\t\t\t\t\t\t\tkkcroeb_256_256_80_s_c1_c_t_0_0_1.jpg", "event_id": "29097889", "artist_id": 7013269, "time": null, "venue_img": "lincoln-hall"}, {"venue": "Schubas", "artist_name": "Pomo", "band_img": "https://mohawkaustin.com/_/made/_/remote/https_res.\t\t\t\t\t\t\tcloudinary.com/hjbfjdt7p/image/upload/c_fill,w_470/v1467240024/neqbteulerpqi\t\t\t\t\t\t\tkkcroeb_256_256_80_s_c1_c_t_0_0_1.jpg", "event_id": "29712819", "artist_id": 1553001, "time": null, "venue_img": "schubas"}]], ["2017-05-17", [{"venue": "Quenchers", "artist_name": "Dogs at Large", "band_img": "https://mohawkaustin.com/_/made/_/remote/https_res.\t\t\t\t\t\t\tcloudinary.com/hjbfjdt7p/image/upload/c_fill,w_470/v1467240024/neqbteulerpqi\t\t\t\t\t\t\tkkcroeb_256_256_80_s_c1_c_t_0_0_1.jpg", "event_id": "29866654", "artist_id": 8668699, "time": "21:00:00", "venue_img": "quenchers"}, {"venue": "Bottom Lounge", "artist_name": "The Story So Far", "band_img": "https://mohawkaustin.com/_/made/_/remote/https_res.\t\t\t\t\t\t\tcloudinary.com/hjbfjdt7p/image/upload/c_fill,w_470/v1467240024/neqbteulerpqi\t\t\t\t\t\t\tkkcroeb_256_256_80_s_c1_c_t_0_0_1.jpg", "event_id": "29315469", "artist_id": 219967, "time": "19:00:00", "venue_img": "bottom-lounge"}, {"venue": "Beat Kitchen", "artist_name": "North", "band_img": "https://mohawkaustin.com/_/made/_/remote/https_res.\t\t\t\t\t\t\tcloudinary.com/hjbfjdt7p/image/upload/c_fill,w_470/v1467240024/neqbteulerpqi\t\t\t\t\t\t\tkkcroeb_256_256_80_s_c1_c_t_0_0_1.jpg", "event_id": "29173474", "artist_id": 359008, "time": "20:30:00", "venue_img": "beat-kitchen"}, {"venue": "Lincoln Hall", "artist_name": "Pantha du Prince", "band_img": "https://mohawkaustin.com/_/made/_/remote/https_res.\t\t\t\t\t\t\tcloudinary.com/hjbfjdt7p/image/upload/c_fill,w_470/v1467240024/neqbteulerpqi\t\t\t\t\t\t\tkkcroeb_256_256_80_s_c1_c_t_0_0_1.jpg", "event_id": "29461379", "artist_id": 318700, "time": "19:00:00", "venue_img": "lincoln-hall"}, {"venue": "Schubas", "artist_name": "Nick Thune", "band_img": "https://mohawkaustin.com/_/made/_/remote/https_res.\t\t\t\t\t\t\tcloudinary.com/hjbfjdt7p/image/upload/c_fill,w_470/v1467240024/neqbteulerpqi\t\t\t\t\t\t\tkkcroeb_256_256_80_s_c1_c_t_0_0_1.jpg", "event_id": "29885479", "artist_id": 566971, "time": "21:30:00", "venue_img": "schubas"}, {"venue": "The Hideout", "artist_name": "Spacebeach", "band_img": "https://mohawkaustin.com/_/made/_/remote/https_res.\t\t\t\t\t\t\tcloudinary.com/hjbfjdt7p/image/upload/c_fill,w_470/v1467240024/neqbteulerpqi\t\t\t\t\t\t\tkkcroeb_256_256_80_s_c1_c_t_0_0_1.jpg", "event_id": "29949059", "artist_id": 4114606, "time": "21:00:00", "venue_img": "hideout"}]], ["2017-05-18", [{"venue": "Empty Bottle", "artist_name": "Jambinai", "band_img": "https://mohawkaustin.com/_/made/_/remote/https_res.\t\t\t\t\t\t\tcloudinary.com/hjbfjdt7p/image/upload/c_fill,w_470/v1467240024/neqbteulerpqi\t\t\t\t\t\t\tkkcroeb_256_256_80_s_c1_c_t_0_0_1.jpg", "event_id": "29038354", "artist_id": 7785269, "time": "21:00:00", "venue_img": "empty-bottle"}, {"venue": "Bottom Lounge", "artist_name": "The Story So Far", "band_img": "https://mohawkaustin.com/_/made/_/remote/https_res.\t\t\t\t\t\t\tcloudinary.com/hjbfjdt7p/image/upload/c_fill,w_470/v1467240024/neqbteulerpqi\t\t\t\t\t\t\tkkcroeb_256_256_80_s_c1_c_t_0_0_1.jpg", "event_id": "29553689", "artist_id": 219967, "time": "19:00:00", "venue_img": "bottom-lounge"}, {"venue": "Subterranean", "artist_name": "Arkona", "band_img": "https://mohawkaustin.com/_/made/_/remote/https_res.\t\t\t\t\t\t\tcloudinary.com/hjbfjdt7p/image/upload/c_fill,w_470/v1467240024/neqbteulerpqi\t\t\t\t\t\t\tkkcroeb_256_256_80_s_c1_c_t_0_0_1.jpg", "event_id": "29272679", "artist_id": 232814, "time": "19:30:00", "venue_img": "subterranean"}, {"venue": "Beat Kitchen", "artist_name": "Savoy Motel", "band_img": "https://mohawkaustin.com/_/made/_/remote/https_res.\t\t\t\t\t\t\tcloudinary.com/hjbfjdt7p/image/upload/c_fill,w_470/v1467240024/neqbteulerpqi\t\t\t\t\t\t\tkkcroeb_256_256_80_s_c1_c_t_0_0_1.jpg", "event_id": "29720829", "artist_id": 8595204, "time": "20:30:00", "venue_img": "beat-kitchen"}, {"venue": "Lincoln Hall", "artist_name": "North Mississippi Allstars", "band_img": "https://mohawkaustin.com/_/made/_/remote/https_res.\t\t\t\t\t\t\tcloudinary.com/hjbfjdt7p/image/upload/c_fill,w_470/v1467240024/neqbteulerpqi\t\t\t\t\t\t\tkkcroeb_256_256_80_s_c1_c_t_0_0_1.jpg", "event_id": "29809169", "artist_id": 27001, "time": null, "venue_img": "lincoln-hall"}, {"venue": "Schubas", "artist_name": "The Family Crest", "band_img": "https://mohawkaustin.com/_/made/_/remote/https_res.\t\t\t\t\t\t\tcloudinary.com/hjbfjdt7p/image/upload/c_fill,w_470/v1467240024/neqbteulerpqi\t\t\t\t\t\t\tkkcroeb_256_256_80_s_c1_c_t_0_0_1.jpg", "event_id": "29673369", "artist_id": 2391409, "time": "20:00:00", "venue_img": "schubas"}, {"venue": "The Hideout", "artist_name": "Devil in a Woodpile", "band_img": "https://mohawkaustin.com/_/made/_/remote/https_res.\t\t\t\t\t\t\tcloudinary.com/hjbfjdt7p/image/upload/c_fill,w_470/v1467240024/neqbteulerpqi\t\t\t\t\t\t\tkkcroeb_256_256_80_s_c1_c_t_0_0_1.jpg", "event_id": "29949064", "artist_id": 199723, "time": "18:00:00", "venue_img": "hideout"}]], ["2017-05-19", [{"venue": "Empty Bottle", "artist_name": "Big Freedia", "band_img": "https://mohawkaustin.com/_/made/_/remote/https_res.\t\t\t\t\t\t\tcloudinary.com/hjbfjdt7p/image/upload/c_fill,w_470/v1467240024/neqbteulerpqi\t\t\t\t\t\t\tkkcroeb_256_256_80_s_c1_c_t_0_0_1.jpg", "event_id": "29719269", "artist_id": 2490586, "time": "21:00:00", "venue_img": "empty-bottle"}, {"venue": "Quenchers", "artist_name": "Sons of Ra", "band_img": "https://mohawkaustin.com/_/made/_/remote/https_res.\t\t\t\t\t\t\tcloudinary.com/hjbfjdt7p/image/upload/c_fill,w_470/v1467240024/neqbteulerpqi\t\t\t\t\t\t\tkkcroeb_256_256_80_s_c1_c_t_0_0_1.jpg", "event_id": "29651949", "artist_id": 8938009, "time": "21:00:00", "venue_img": "quenchers"}, {"venue": "Bottom Lounge", "artist_name": "Tall Heights", "band_img": "https://mohawkaustin.com/_/made/_/remote/https_res.\t\t\t\t\t\t\tcloudinary.com/hjbfjdt7p/image/upload/c_fill,w_470/v1467240024/neqbteulerpqi\t\t\t\t\t\t\tkkcroeb_256_256_80_s_c1_c_t_0_0_1.jpg", "event_id": "29635184", "artist_id": 1370015, "time": null, "venue_img": "bottom-lounge"}, {"venue": "Subterranean", "artist_name": "Vancouver Sleep Clinic", "band_img": "https://mohawkaustin.com/_/made/_/remote/https_res.\t\t\t\t\t\t\tcloudinary.com/hjbfjdt7p/image/upload/c_fill,w_470/v1467240024/neqbteulerpqi\t\t\t\t\t\t\tkkcroeb_256_256_80_s_c1_c_t_0_0_1.jpg", "event_id": "29676939", "artist_id": 7562669, "time": "20:30:00", "venue_img": "subterranean"}, {"venue": "Beat Kitchen", "artist_name": "Ballyhoo!", "band_img": "https://mohawkaustin.com/_/made/_/remote/https_res.\t\t\t\t\t\t\tcloudinary.com/hjbfjdt7p/image/upload/c_fill,w_470/v1467240024/neqbteulerpqi\t\t\t\t\t\t\tkkcroeb_256_256_80_s_c1_c_t_0_0_1.jpg", "event_id": "29654234", "artist_id": 181575, "time": "20:00:00", "venue_img": "beat-kitchen"}, {"venue": "Lincoln Hall", "artist_name": "Meat Puppets", "band_img": "https://mohawkaustin.com/_/made/_/remote/https_res.\t\t\t\t\t\t\tcloudinary.com/hjbfjdt7p/image/upload/c_fill,w_470/v1467240024/neqbteulerpqi\t\t\t\t\t\t\tkkcroeb_256_256_80_s_c1_c_t_0_0_1.jpg", "event_id": "29627734", "artist_id": 207453, "time": null, "venue_img": "lincoln-hall"}, {"venue": "Schubas", "artist_name": "Pert Near Sandstone", "band_img": "https://mohawkaustin.com/_/made/_/remote/https_res.\t\t\t\t\t\t\tcloudinary.com/hjbfjdt7p/image/upload/c_fill,w_470/v1467240024/neqbteulerpqi\t\t\t\t\t\t\tkkcroeb_256_256_80_s_c1_c_t_0_0_1.jpg", "event_id": "29837054", "artist_id": 207070, "time": null, "venue_img": "schubas"}, {"venue": "The Hideout", "artist_name": "Big Sadie", "band_img": "https://mohawkaustin.com/_/made/_/remote/https_res.\t\t\t\t\t\t\tcloudinary.com/hjbfjdt7p/image/upload/c_fill,w_470/v1467240024/neqbteulerpqi\t\t\t\t\t\t\tkkcroeb_256_256_80_s_c1_c_t_0_0_1.jpg", "event_id": "29788919", "artist_id": 8617994, "time": "21:00:00", "venue_img": "hideout"}, {"venue": "The Hideout", "artist_name": "Jodee Lewis", "band_img": "https://mohawkaustin.com/_/made/_/remote/https_res.\t\t\t\t\t\t\tcloudinary.com/hjbfjdt7p/image/upload/c_fill,w_470/v1467240024/neqbteulerpqi\t\t\t\t\t\t\tkkcroeb_256_256_80_s_c1_c_t_0_0_1.jpg", "event_id": "30043554", "artist_id": 5498138, "time": "18:00:00", "venue_img": "hideout"}]], ["2017-05-20", [{"venue": "Empty Bottle", "artist_name": "Ha Ha Tonka", "band_img": "https://mohawkaustin.com/_/made/_/remote/https_res.\t\t\t\t\t\t\tcloudinary.com/hjbfjdt7p/image/upload/c_fill,w_470/v1467240024/neqbteulerpqi\t\t\t\t\t\t\tkkcroeb_256_256_80_s_c1_c_t_0_0_1.jpg", "event_id": "28959349", "artist_id": 569454, "time": "21:00:00", "venue_img": "empty-bottle"}, {"venue": "Bottom Lounge", "artist_name": "The Birthday Massacre", "band_img": "https://mohawkaustin.com/_/made/_/remote/https_res.\t\t\t\t\t\t\tcloudinary.com/hjbfjdt7p/image/upload/c_fill,w_470/v1467240024/neqbteulerpqi\t\t\t\t\t\t\tkkcroeb_256_256_80_s_c1_c_t_0_0_1.jpg", "event_id": "29719294", "artist_id": 95347, "time": "20:00:00", "venue_img": "bottom-lounge"}, {"venue": "Subterranean", "artist_name": "Hotel Garuda", "band_img": "https://mohawkaustin.com/_/made/_/remote/https_res.\t\t\t\t\t\t\tcloudinary.com/hjbfjdt7p/image/upload/c_fill,w_470/v1467240024/neqbteulerpqi\t\t\t\t\t\t\tkkcroeb_256_256_80_s_c1_c_t_0_0_1.jpg", "event_id": "29377164", "artist_id": 8332508, "time": "21:00:00", "venue_img": "subterranean"}, {"venue": "Subterranean", "artist_name": "Coffin Hollow", "band_img": "https://mohawkaustin.com/_/made/_/remote/https_res.\t\t\t\t\t\t\tcloudinary.com/hjbfjdt7p/image/upload/c_fill,w_470/v1467240024/neqbteulerpqi\t\t\t\t\t\t\tkkcroeb_256_256_80_s_c1_c_t_0_0_1.jpg", "event_id": "29680249", "artist_id": 9063274, "time": "20:00:00", "venue_img": "subterranean"}, {"venue": "Lincoln Hall", "artist_name": "Oddisee with GOOD COMPNY", "band_img": "https://mohawkaustin.com/_/made/_/remote/https_res.\t\t\t\t\t\t\tcloudinary.com/hjbfjdt7p/image/upload/c_fill,w_470/v1467240024/neqbteulerpqi\t\t\t\t\t\t\tkkcroeb_256_256_80_s_c1_c_t_0_0_1.jpg", "event_id": "29781569", "artist_id": 8579499, "time": "20:00:00", "venue_img": "lincoln-hall"}, {"venue": "Thalia Hall", "artist_name": "Justin Townes Earle", "band_img": "https://mohawkaustin.com/_/made/_/remote/https_res.\t\t\t\t\t\t\tcloudinary.com/hjbfjdt7p/image/upload/c_fill,w_470/v1467240024/neqbteulerpqi\t\t\t\t\t\t\tkkcroeb_256_256_80_s_c1_c_t_0_0_1.jpg", "event_id": "29289734", "artist_id": 455107, "time": "20:00:00", "venue_img": "thalia-hall"}, {"venue": "The Hideout", "artist_name": "Eddie Pepitone", "band_img": "https://mohawkaustin.com/_/made/_/remote/https_res.\t\t\t\t\t\t\tcloudinary.com/hjbfjdt7p/image/upload/c_fill,w_470/v1467240024/neqbteulerpqi\t\t\t\t\t\t\tkkcroeb_256_256_80_s_c1_c_t_0_0_1.jpg", "event_id": "29775159", "artist_id": 2085885, "time": "20:00:00", "venue_img": "hideout"}, {"venue": "The Hideout", "artist_name": "Eddie Pepitone", "band_img": "https://mohawkaustin.com/_/made/_/remote/https_res.\t\t\t\t\t\t\tcloudinary.com/hjbfjdt7p/image/upload/c_fill,w_470/v1467240024/neqbteulerpqi\t\t\t\t\t\t\tkkcroeb_256_256_80_s_c1_c_t_0_0_1.jpg", "event_id": "29775169", "artist_id": 2085885, "time": "22:00:00", "venue_img": "hideout"}]], ["2017-05-21", [{"venue": "Empty Bottle", "artist_name": "Windhand", "band_img": "https://mohawkaustin.com/_/made/_/remote/https_res.\t\t\t\t\t\t\tcloudinary.com/hjbfjdt7p/image/upload/c_fill,w_470/v1467240024/neqbteulerpqi\t\t\t\t\t\t\tkkcroeb_256_256_80_s_c1_c_t_0_0_1.jpg", "event_id": "29361009", "artist_id": 3619161, "time": "21:00:00", "venue_img": "empty-bottle"}, {"venue": "Quenchers", "artist_name": "Elephant Gun", "band_img": "https://mohawkaustin.com/_/made/_/remote/https_res.\t\t\t\t\t\t\tcloudinary.com/hjbfjdt7p/image/upload/c_fill,w_470/v1467240024/neqbteulerpqi\t\t\t\t\t\t\tkkcroeb_256_256_80_s_c1_c_t_0_0_1.jpg", "event_id": "29734694", "artist_id": 354463, "time": "21:00:00", "venue_img": "quenchers"}, {"venue": "Bottom Lounge", "artist_name": "JMSN", "band_img": "https://mohawkaustin.com/_/made/_/remote/https_res.\t\t\t\t\t\t\tcloudinary.com/hjbfjdt7p/image/upload/c_fill,w_470/v1467240024/neqbteulerpqi\t\t\t\t\t\t\tkkcroeb_256_256_80_s_c1_c_t_0_0_1.jpg", "event_id": "29456949", "artist_id": 5250053, "time": "20:00:00", "venue_img": "bottom-lounge"}, {"venue": "Beat Kitchen", "artist_name": "Arlie", "band_img": "https://mohawkaustin.com/_/made/_/remote/https_res.\t\t\t\t\t\t\tcloudinary.com/hjbfjdt7p/image/upload/c_fill,w_470/v1467240024/neqbteulerpqi\t\t\t\t\t\t\tkkcroeb_256_256_80_s_c1_c_t_0_0_1.jpg", "event_id": "29899624", "artist_id": 9077774, "time": "20:30:00", "venue_img": "beat-kitchen"}, {"venue": "Lincoln Hall", "artist_name": "The Weeks", "band_img": "https://mohawkaustin.com/_/made/_/remote/https_res.\t\t\t\t\t\t\tcloudinary.com/hjbfjdt7p/image/upload/c_fill,w_470/v1467240024/neqbteulerpqi\t\t\t\t\t\t\tkkcroeb_256_256_80_s_c1_c_t_0_0_1.jpg", "event_id": "29489144", "artist_id": 674254, "time": null, "venue_img": "lincoln-hall"}, {"venue": "Thalia Hall", "artist_name": "Kiefer Sutherland", "band_img": "https://mohawkaustin.com/_/made/_/remote/https_res.\t\t\t\t\t\t\tcloudinary.com/hjbfjdt7p/image/upload/c_fill,w_470/v1467240024/neqbteulerpqi\t\t\t\t\t\t\tkkcroeb_256_256_80_s_c1_c_t_0_0_1.jpg", "event_id": "29113264", "artist_id": 8771489, "time": null, "venue_img": "thalia-hall"}, {"venue": "The Hideout", "artist_name": "Fake Limbs", "band_img": "https://mohawkaustin.com/_/made/_/remote/https_res.\t\t\t\t\t\t\tcloudinary.com/hjbfjdt7p/image/upload/c_fill,w_470/v1467240024/neqbteulerpqi\t\t\t\t\t\t\tkkcroeb_256_256_80_s_c1_c_t_0_0_1.jpg", "event_id": "29949129", "artist_id": 4661523, "time": "21:00:00", "venue_img": "hideout"}]], ["2017-05-22", [{"venue": "Empty Bottle", "artist_name": "Bloom (Chicago)", "band_img": "https://mohawkaustin.com/_/made/_/remote/https_res.\t\t\t\t\t\t\tcloudinary.com/hjbfjdt7p/image/upload/c_fill,w_470/v1467240024/neqbteulerpqi\t\t\t\t\t\t\tkkcroeb_256_256_80_s_c1_c_t_0_0_1.jpg", "event_id": "29831709", "artist_id": 9080399, "time": "08:00:00", "venue_img": "empty-bottle"}, {"venue": "Beat Kitchen", "artist_name": "Extraordinary Popular Delusions", "band_img": "https://mohawkaustin.com/_/made/_/remote/https_res.\t\t\t\t\t\t\tcloudinary.com/hjbfjdt7p/image/upload/c_fill,w_470/v1467240024/neqbteulerpqi\t\t\t\t\t\t\tkkcroeb_256_256_80_s_c1_c_t_0_0_1.jpg", "event_id": "29979719", "artist_id": 3099761, "time": "21:00:00", "venue_img": "beat-kitchen"}, {"venue": "Schubas", "artist_name": "Sir Richard Bishop", "band_img": "https://mohawkaustin.com/_/made/_/remote/https_res.\t\t\t\t\t\t\tcloudinary.com/hjbfjdt7p/image/upload/c_fill,w_470/v1467240024/neqbteulerpqi\t\t\t\t\t\t\tkkcroeb_256_256_80_s_c1_c_t_0_0_1.jpg", "event_id": "29506559", "artist_id": 153637, "time": null, "venue_img": "schubas"}, {"venue": "Thalia Hall", "artist_name": "Murder City Devils", "band_img": "https://mohawkaustin.com/_/made/_/remote/https_res.\t\t\t\t\t\t\tcloudinary.com/hjbfjdt7p/image/upload/c_fill,w_470/v1467240024/neqbteulerpqi\t\t\t\t\t\t\tkkcroeb_256_256_80_s_c1_c_t_0_0_1.jpg", "event_id": "29516249", "artist_id": 318593, "time": "20:30:00", "venue_img": "thalia-hall"}, {"venue": "The Hideout", "artist_name": "Ralph White", "band_img": "https://mohawkaustin.com/_/made/_/remote/https_res.\t\t\t\t\t\t\tcloudinary.com/hjbfjdt7p/image/upload/c_fill,w_470/v1467240024/neqbteulerpqi\t\t\t\t\t\t\tkkcroeb_256_256_80_s_c1_c_t_0_0_1.jpg", "event_id": "29744104", "artist_id": 5590, "time": "19:00:00", "venue_img": "hideout"}]], ["2017-05-23", [{"venue": "Empty Bottle", "artist_name": "Slushy", "band_img": "https://mohawkaustin.com/_/made/_/remote/https_res.\t\t\t\t\t\t\tcloudinary.com/hjbfjdt7p/image/upload/c_fill,w_470/v1467240024/neqbteulerpqi\t\t\t\t\t\t\tkkcroeb_256_256_80_s_c1_c_t_0_0_1.jpg", "event_id": "29909904", "artist_id": 3705866, "time": "21:00:00", "venue_img": "empty-bottle"}, {"venue": "Bottom Lounge", "artist_name": "Wavves", "band_img": "https://mohawkaustin.com/_/made/_/remote/https_res.\t\t\t\t\t\t\tcloudinary.com/hjbfjdt7p/image/upload/c_fill,w_470/v1467240024/neqbteulerpqi\t\t\t\t\t\t\tkkcroeb_256_256_80_s_c1_c_t_0_0_1.jpg", "event_id": "29451669", "artist_id": 2360100, "time": null, "venue_img": "bottom-lounge"}, {"venue": "Subterranean", "artist_name": "Frank Knight", "band_img": "https://mohawkaustin.com/_/made/_/remote/https_res.\t\t\t\t\t\t\tcloudinary.com/hjbfjdt7p/image/upload/c_fill,w_470/v1467240024/neqbteulerpqi\t\t\t\t\t\t\tkkcroeb_256_256_80_s_c1_c_t_0_0_1.jpg", "event_id": "30024834", "artist_id": 8336568, "time": "21:00:00", "venue_img": "subterranean"}, {"venue": "Lincoln Hall", "artist_name": "Outrun the Sunlight", "band_img": "https://mohawkaustin.com/_/made/_/remote/https_res.\t\t\t\t\t\t\tcloudinary.com/hjbfjdt7p/image/upload/c_fill,w_470/v1467240024/neqbteulerpqi\t\t\t\t\t\t\tkkcroeb_256_256_80_s_c1_c_t_0_0_1.jpg", "event_id": "29781604", "artist_id": 7807649, "time": "19:00:00", "venue_img": "lincoln-hall"}, {"venue": "The Hideout", "artist_name": "David Singer & The Sweet Science", "band_img": "https://mohawkaustin.com/_/made/_/remote/https_res.\t\t\t\t\t\t\tcloudinary.com/hjbfjdt7p/image/upload/c_fill,w_470/v1467240024/neqbteulerpqi\t\t\t\t\t\t\tkkcroeb_256_256_80_s_c1_c_t_0_0_1.jpg", "event_id": "29775229", "artist_id": 251650, "time": "21:00:00", "venue_img": "hideout"}]], ["2017-05-24", [{"venue": "Subterranean", "artist_name": "Saint Millie", "band_img": "https://mohawkaustin.com/_/made/_/remote/https_res.\t\t\t\t\t\t\tcloudinary.com/hjbfjdt7p/image/upload/c_fill,w_470/v1467240024/neqbteulerpqi\t\t\t\t\t\t\tkkcroeb_256_256_80_s_c1_c_t_0_0_1.jpg", "event_id": "29885609", "artist_id": 7456124, "time": "21:00:00", "venue_img": "subterranean"}, {"venue": "Beat Kitchen", "artist_name": "Grandkids", "band_img": "https://mohawkaustin.com/_/made/_/remote/https_res.\t\t\t\t\t\t\tcloudinary.com/hjbfjdt7p/image/upload/c_fill,w_470/v1467240024/neqbteulerpqi\t\t\t\t\t\t\tkkcroeb_256_256_80_s_c1_c_t_0_0_1.jpg", "event_id": "29789039", "artist_id": 3328291, "time": "20:00:00", "venue_img": "beat-kitchen"}, {"venue": "Schubas", "artist_name": "Ripe", "band_img": "https://mohawkaustin.com/_/made/_/remote/https_res.\t\t\t\t\t\t\tcloudinary.com/hjbfjdt7p/image/upload/c_fill,w_470/v1467240024/neqbteulerpqi\t\t\t\t\t\t\tkkcroeb_256_256_80_s_c1_c_t_0_0_1.jpg", "event_id": "29737449", "artist_id": 308245, "time": "20:00:00", "venue_img": "schubas"}, {"venue": "Thalia Hall", "artist_name": "The Record Company", "band_img": "https://mohawkaustin.com/_/made/_/remote/https_res.\t\t\t\t\t\t\tcloudinary.com/hjbfjdt7p/image/upload/c_fill,w_470/v1467240024/neqbteulerpqi\t\t\t\t\t\t\tkkcroeb_256_256_80_s_c1_c_t_0_0_1.jpg", "event_id": "29367764", "artist_id": 5036328, "time": null, "venue_img": "thalia-hall"}, {"venue": "The Hideout", "artist_name": "Desert Limina", "band_img": "https://mohawkaustin.com/_/made/_/remote/https_res.\t\t\t\t\t\t\tcloudinary.com/hjbfjdt7p/image/upload/c_fill,w_470/v1467240024/neqbteulerpqi\t\t\t\t\t\t\tkkcroeb_256_256_80_s_c1_c_t_0_0_1.jpg", "event_id": "30021569", "artist_id": 9100034, "time": "19:00:00", "venue_img": "hideout"}, {"venue": "The Hideout", "artist_name": "Desert Limina", "band_img": "https://mohawkaustin.com/_/made/_/remote/https_res.\t\t\t\t\t\t\tcloudinary.com/hjbfjdt7p/image/upload/c_fill,w_470/v1467240024/neqbteulerpqi\t\t\t\t\t\t\tkkcroeb_256_256_80_s_c1_c_t_0_0_1.jpg", "event_id": "30059169", "artist_id": 9100034, "time": "21:00:00", "venue_img": "hideout"}]]]